nflschedule/__init__.py
nflschedule/dates.py
nflschedule/nflschedule.py
nflschedule/data/schedule.csv
nflschedule-0.2.dist-info/LICENSE
nflschedule-0.2.dist-info/METADATA
nflschedule-0.2.dist-info/WHEEL
nflschedule-0.2.dist-info/top_level.txt
nflschedule-0.2.dist-info/RECORD
